README.md
inner.py
setup.py
inner_class.egg-info/PKG-INFO
inner_class.egg-info/SOURCES.txt
inner_class.egg-info/dependency_links.txt
inner_class.egg-info/top_level.txt
inner_class.egg-info/zip-safe